docinfer/__init__.py
docinfer/cli.py
docinfer/hello_world.py
docinfer/models/__init__.py
docinfer/models/config.py
docinfer/models/metadata.py
docinfer/prompts/__init__.py
docinfer/prompts/metadata.py
docinfer/services/__init__.py
docinfer/services/ai_analyzer.py
docinfer/services/output.py
docinfer/services/pdf_extractor.py
docinfer-0.1.1.dist-info/licenses/LICENSE
docinfer-0.1.1.dist-info/METADATA
docinfer-0.1.1.dist-info/WHEEL
docinfer-0.1.1.dist-info/entry_points.txt
docinfer-0.1.1.dist-info/top_level.txt
docinfer-0.1.1.dist-info/RECORD
