Metadata-Version: 2.4
Name: docinfer
Version: 0.1.1
Summary: Extract and infer metadata from PDF documents using AI-powered analysis
Author-email: Tino Kanngiesser <tinokanngiesser@gmail.com>
License: MIT
Project-URL: Homepage, https://github.com/tidyeval/docinfer
Project-URL: Repository, https://github.com/tidyeval/docinfer
Project-URL: BugTracker, https://github.com/tidyeval/docinfer/issues
Keywords: pdf,metadata,extraction,ai,llm
Classifier: Development Status :: 3 - Alpha
Classifier: Intended Audience :: Developers
Classifier: License :: OSI Approved :: MIT License
Classifier: Programming Language :: Python :: 3
Classifier: Programming Language :: Python :: 3.12
Requires-Python: >=3.12
License-File: LICENSE
Requires-Dist: pydantic>=2.0.0
Requires-Dist: langchain-ollama>=0.2.0
Requires-Dist: pypdf>=4.0.0
Requires-Dist: numpy>=1.24.0
Requires-Dist: pandas>=2.0.0
Requires-Dist: requests>=2.31.0
Requires-Dist: python-dotenv>=1.0.0
Requires-Dist: typer>=0.12.0
Requires-Dist: rich>=13.0.0
Provides-Extra: dev
Requires-Dist: pytest<9.0.0,>=8.3.3; extra == "dev"
Requires-Dist: pytest-cov>=4.0.0; extra == "dev"
Requires-Dist: pytest-mock>=3.14.0; extra == "dev"
Requires-Dist: black>=23.0.0; extra == "dev"
Requires-Dist: ruff>=0.1.0; extra == "dev"
Dynamic: license-file
